[
  {
    "title": "인공지능 MLOps 플랫폼 백엔드 개발자 (자바/5년 이상)",
    "link": "https://www.saramin.co.kr/zf_user/jobs/relay/view?view_type=search&rec_idx=52253675&location=ts&searchword=%EB%B0%B1%EC%97%94%EB%93%9C+%EC%9E%90%EB%B0%94&searchType=search&paid_fl=n&search_uuid=944ec723-8132-4ae0-8014-45f87586a32f",
    "source": "Saramin"
  },
  {
    "title": "[대구] Java 자바 백엔드 개발자 채용",
    "link": "https://www.saramin.co.kr/zf_user/jobs/relay/view?view_type=search&rec_idx=52371096&location=ts&searchword=%EB%B0%B1%EC%97%94%EB%93%9C+%EC%9E%90%EB%B0%94&searchType=search&paid_fl=n&search_uuid=944ec723-8132-4ae0-8014-45f87586a32f",
    "source": "Saramin"
  },
  {
    "title": "자바 백엔드 프로그램 개발 대리~과(차)장급 경력사원 모집(6명)",
    "link": "https://www.saramin.co.kr/zf_user/jobs/relay/view?view_type=search&rec_idx=52439076&location=ts&searchword=%EB%B0%B1%EC%97%94%EB%93%9C+%EC%9E%90%EB%B0%94&searchType=search&paid_fl=n&search_uuid=944ec723-8132-4ae0-8014-45f87586a32f",
    "source": "Saramin"
  },
  {
    "title": "백엔드 엔지니어(Java, Server-side)",
    "link": "https://www.saramin.co.kr/zf_user/jobs/relay/view?view_type=search&rec_idx=52252453&location=ts&searchword=%EB%B0%B1%EC%97%94%EB%93%9C+%EC%9E%90%EB%B0%94&searchType=search&paid_fl=n&search_uuid=944ec723-8132-4ae0-8014-45f87586a32f",
    "source": "Saramin"
  },
  {
    "title": "JAVA 백엔드 웹개발자 채용",
    "link": "https://www.saramin.co.kr/zf_user/jobs/relay/view?view_type=search&rec_idx=52144205&location=ts&searchword=%EB%B0%B1%EC%97%94%EB%93%9C+%EC%9E%90%EB%B0%94&searchType=search&paid_fl=n&search_uuid=944ec723-8132-4ae0-8014-45f87586a32f",
    "source": "Saramin"
  },
  {
    "title": "위라클 JAVA 백엔드 개발자 모집 [프리랜서 채용]",
    "link": "https://www.saramin.co.kr/zf_user/jobs/relay/view?view_type=search&rec_idx=52385264&location=ts&searchword=%EB%B0%B1%EC%97%94%EB%93%9C+%EC%9E%90%EB%B0%94&searchType=search&paid_fl=n&search_uuid=944ec723-8132-4ae0-8014-45f87586a32f",
    "source": "Saramin"
  },
  {
    "title": "위라클 JAVA 백엔드 개발자 모집 [정규직 채용]",
    "link": "https://www.saramin.co.kr/zf_user/jobs/relay/view?view_type=search&rec_idx=52379696&location=ts&searchword=%EB%B0%B1%EC%97%94%EB%93%9C+%EC%9E%90%EB%B0%94&searchType=search&paid_fl=n&search_uuid=944ec723-8132-4ae0-8014-45f87586a32f",
    "source": "Saramin"
  },
  {
    "title": "보험/금융 관련 Java Backend 개발자 경력 모집",
    "link": "https://www.saramin.co.kr/zf_user/jobs/relay/view?view_type=search&rec_idx=51603188&location=ts&searchword=%EB%B0%B1%EC%97%94%EB%93%9C+%EC%9E%90%EB%B0%94&searchType=search&paid_fl=n&search_uuid=944ec723-8132-4ae0-8014-45f87586a32f",
    "source": "Saramin"
  },
  {
    "title": "[글로벌 코스닥 상장사]씨티케이 JAVA 백엔드 개발자 채용",
    "link": "https://www.saramin.co.kr/zf_user/jobs/relay/view?view_type=search&rec_idx=52238528&location=ts&searchword=%EB%B0%B1%EC%97%94%EB%93%9C+%EC%9E%90%EB%B0%94&searchType=search&paid_fl=n&search_uuid=944ec723-8132-4ae0-8014-45f87586a32f",
    "source": "Saramin"
  },
  {
    "title": "[서초/정규직] 클라우드 백엔드 개발자(Spring/Java) 채용",
    "link": "https://www.saramin.co.kr/zf_user/jobs/relay/view?view_type=search&rec_idx=52288178&location=ts&searchword=%EB%B0%B1%EC%97%94%EB%93%9C+%EC%9E%90%EB%B0%94&searchType=search&paid_fl=n&search_uuid=944ec723-8132-4ae0-8014-45f87586a32f",
    "source": "Saramin"
  },
  {
    "title": "[NHN KCP] Java 백엔드 웹개발자(사원/대리급)",
    "link": "https://www.saramin.co.kr/zf_user/jobs/relay/view?view_type=search&rec_idx=52384059&location=ts&searchword=%EB%B0%B1%EC%97%94%EB%93%9C+%EC%9E%90%EB%B0%94&searchType=search&paid_fl=n&search_uuid=944ec723-8132-4ae0-8014-45f87586a32f",
    "source": "Saramin"
  },
  {
    "title": "[신입/경력] JAVA 웹/앱 백엔드 개발자 모집",
    "link": "https://www.saramin.co.kr/zf_user/jobs/relay/view?view_type=search&rec_idx=52419628&location=ts&searchword=%EB%B0%B1%EC%97%94%EB%93%9C+%EC%9E%90%EB%B0%94&searchType=search&paid_fl=n&search_uuid=944ec723-8132-4ae0-8014-45f87586a32f",
    "source": "Saramin"
  },
  {
    "title": "(주)모비젠 JAVA / Python 백엔드 서버 개발자 모집",
    "link": "https://www.saramin.co.kr/zf_user/jobs/relay/view?view_type=search&rec_idx=52431653&location=ts&searchword=%EB%B0%B1%EC%97%94%EB%93%9C+%EC%9E%90%EB%B0%94&searchType=search&paid_fl=n&search_uuid=944ec723-8132-4ae0-8014-45f87586a32f",
    "source": "Saramin"
  },
  {
    "title": "백엔드 개발자 모집 (C, JAVA) (신입/경력)",
    "link": "https://www.saramin.co.kr/zf_user/jobs/relay/view?view_type=search&rec_idx=52327817&location=ts&searchword=%EB%B0%B1%EC%97%94%EB%93%9C+%EC%9E%90%EB%B0%94&searchType=search&paid_fl=n&search_uuid=944ec723-8132-4ae0-8014-45f87586a32f",
    "source": "Saramin"
  },
  {
    "title": "[CEMWARE.Inc] Java 백엔드 개발자 채용",
    "link": "https://www.saramin.co.kr/zf_user/jobs/relay/view?view_type=search&rec_idx=52371640&location=ts&searchword=%EB%B0%B1%EC%97%94%EB%93%9C+%EC%9E%90%EB%B0%94&searchType=search&paid_fl=n&search_uuid=944ec723-8132-4ae0-8014-45f87586a32f",
    "source": "Saramin"
  },
  {
    "title": "[정규직][정부과제] 모니터링시스템 JAVA Spring 백앤드개발모집",
    "link": "https://www.saramin.co.kr/zf_user/jobs/relay/view?view_type=search&rec_idx=52338255&location=ts&searchword=%EB%B0%B1%EC%97%94%EB%93%9C+%EC%9E%90%EB%B0%94&searchType=search&paid_fl=n&search_uuid=944ec723-8132-4ae0-8014-45f87586a32f",
    "source": "Saramin"
  },
  {
    "title": "IT Front/Backend JAVA 개발자 채용(경력)",
    "link": "https://www.saramin.co.kr/zf_user/jobs/relay/view?view_type=search&rec_idx=52280299&location=ts&searchword=%EB%B0%B1%EC%97%94%EB%93%9C+%EC%9E%90%EB%B0%94&searchType=search&paid_fl=n&search_uuid=944ec723-8132-4ae0-8014-45f87586a32f",
    "source": "Saramin"
  },
  {
    "title": "Java Backend 서비스 개발자 모집",
    "link": "https://www.saramin.co.kr/zf_user/jobs/relay/view?view_type=search&rec_idx=52394968&location=ts&searchword=%EB%B0%B1%EC%97%94%EB%93%9C+%EC%9E%90%EB%B0%94&searchType=search&paid_fl=n&search_uuid=944ec723-8132-4ae0-8014-45f87586a32f",
    "source": "Saramin"
  },
  {
    "title": "오픈마켓 플랫폼 Java 백엔드 경력 개발자 채용합니다(선정릉역)",
    "link": "https://www.saramin.co.kr/zf_user/jobs/relay/view?view_type=search&rec_idx=52106158&location=ts&searchword=%EB%B0%B1%EC%97%94%EB%93%9C+%EC%9E%90%EB%B0%94&searchType=search&paid_fl=n&search_uuid=944ec723-8132-4ae0-8014-45f87586a32f",
    "source": "Saramin"
  },
  {
    "title": "풀스택(BE/FE), 백엔드/프론트,JAVA 개발자,경력직(배포경험)",
    "link": "https://www.saramin.co.kr/zf_user/jobs/relay/view?view_type=search&rec_idx=52378145&location=ts&searchword=%EB%B0%B1%EC%97%94%EB%93%9C+%EC%9E%90%EB%B0%94&searchType=search&paid_fl=n&search_uuid=944ec723-8132-4ae0-8014-45f87586a32f",
    "source": "Saramin"
  },
  {
    "title": "[악보바다] JAVA, 프론트, 백엔드, 모바일 개발자 모집",
    "link": "https://www.saramin.co.kr/zf_user/jobs/relay/view?view_type=search&rec_idx=52401290&location=ts&searchword=%EB%B0%B1%EC%97%94%EB%93%9C+%EC%9E%90%EB%B0%94&searchType=search&paid_fl=n&search_uuid=944ec723-8132-4ae0-8014-45f87586a32f",
    "source": "Saramin"
  },
  {
    "title": "[판교/글로벌기업] 백엔드 개발자 (Java)",
    "link": "https://www.saramin.co.kr/zf_user/jobs/relay/view?view_type=search&rec_idx=52331186&location=ts&searchword=%EB%B0%B1%EC%97%94%EB%93%9C+%EC%9E%90%EB%B0%94&searchType=search&paid_fl=n&search_uuid=944ec723-8132-4ae0-8014-45f87586a32f",
    "source": "Saramin"
  },
  {
    "title": "(주)엔텔스 JAVA,Spring기반 백엔드 개발자 채용(나주 혁신도시)",
    "link": "https://www.saramin.co.kr/zf_user/jobs/relay/view?view_type=search&rec_idx=52143048&location=ts&searchword=%EB%B0%B1%EC%97%94%EB%93%9C+%EC%9E%90%EB%B0%94&searchType=search&paid_fl=n&search_uuid=944ec723-8132-4ae0-8014-45f87586a32f",
    "source": "Saramin"
  },
  {
    "title": "기술연구소 백엔드/서버/Java/C# 경력 개발자",
    "link": "https://www.saramin.co.kr/zf_user/jobs/relay/view?view_type=search&rec_idx=52027436&location=ts&searchword=%EB%B0%B1%EC%97%94%EB%93%9C+%EC%9E%90%EB%B0%94&searchType=search&paid_fl=n&search_uuid=944ec723-8132-4ae0-8014-45f87586a32f",
    "source": "Saramin"
  },
  {
    "title": "[경력] JAVA 백엔드 개발자 정규직 채용 공고",
    "link": "https://www.saramin.co.kr/zf_user/jobs/relay/view?view_type=search&rec_idx=52440770&location=ts&searchword=%EB%B0%B1%EC%97%94%EB%93%9C+%EC%9E%90%EB%B0%94&searchType=search&paid_fl=n&search_uuid=944ec723-8132-4ae0-8014-45f87586a32f",
    "source": "Saramin"
  },
  {
    "title": "[Web/App software팀] JAVA 백엔드 및 프론트 개발자 모집",
    "link": "https://www.saramin.co.kr/zf_user/jobs/relay/view?view_type=search&rec_idx=52336157&location=ts&searchword=%EB%B0%B1%EC%97%94%EB%93%9C+%EC%9E%90%EB%B0%94&searchType=search&paid_fl=n&search_uuid=944ec723-8132-4ae0-8014-45f87586a32f",
    "source": "Saramin"
  },
  {
    "title": "Java 백엔드 개발자 (11-15년)",
    "link": "https://www.saramin.co.kr/zf_user/jobs/relay/view?view_type=search&rec_idx=52268864&location=ts&searchword=%EB%B0%B1%EC%97%94%EB%93%9C+%EC%9E%90%EB%B0%94&searchType=search&paid_fl=n&search_uuid=944ec723-8132-4ae0-8014-45f87586a32f",
    "source": "Saramin"
  },
  {
    "title": "[HUMAX그룹] 휴맥스 백엔드개발자 모집(Java Spring)",
    "link": "https://www.saramin.co.kr/zf_user/jobs/relay/view?view_type=search&rec_idx=52280305&location=ts&searchword=%EB%B0%B1%EC%97%94%EB%93%9C+%EC%9E%90%EB%B0%94&searchType=search&paid_fl=n&search_uuid=944ec723-8132-4ae0-8014-45f87586a32f",
    "source": "Saramin"
  },
  {
    "title": "[카카오공식딜러사] 백엔드 개발팀 팀장(Go / Java / MariaDB)",
    "link": "https://www.saramin.co.kr/zf_user/jobs/relay/view?view_type=search&rec_idx=52298990&location=ts&searchword=%EB%B0%B1%EC%97%94%EB%93%9C+%EC%9E%90%EB%B0%94&searchType=search&paid_fl=n&search_uuid=944ec723-8132-4ae0-8014-45f87586a32f",
    "source": "Saramin"
  },
  {
    "title": "[백엔드] JAVA 개발자 5~13년 경력 모집",
    "link": "https://www.saramin.co.kr/zf_user/jobs/relay/view?view_type=search&rec_idx=52267878&location=ts&searchword=%EB%B0%B1%EC%97%94%EB%93%9C+%EC%9E%90%EB%B0%94&searchType=search&paid_fl=n&search_uuid=944ec723-8132-4ae0-8014-45f87586a32f",
    "source": "Saramin"
  },
  {
    "title": "서버 개발자 채용 (Java 백엔드 중심 / 시스템 통합 및 고도화)",
    "link": "https://www.saramin.co.kr/zf_user/jobs/relay/view?view_type=search&rec_idx=52253854&location=ts&searchword=%EB%B0%B1%EC%97%94%EB%93%9C+%EC%9E%90%EB%B0%94&searchType=search&paid_fl=n&search_uuid=944ec723-8132-4ae0-8014-45f87586a32f",
    "source": "Saramin"
  },
  {
    "title": "(주)아카이버스 JAVA 백엔드 개발자 경력직 채용",
    "link": "https://www.saramin.co.kr/zf_user/jobs/relay/view?view_type=search&rec_idx=52227864&location=ts&searchword=%EB%B0%B1%EC%97%94%EB%93%9C+%EC%9E%90%EB%B0%94&searchType=search&paid_fl=n&search_uuid=944ec723-8132-4ae0-8014-45f87586a32f",
    "source": "Saramin"
  },
  {
    "title": "Java 백엔드 개발자 모집",
    "link": "https://www.saramin.co.kr/zf_user/jobs/relay/view?view_type=search&rec_idx=52298443&location=ts&searchword=%EB%B0%B1%EC%97%94%EB%93%9C+%EC%9E%90%EB%B0%94&searchType=search&paid_fl=n&search_uuid=944ec723-8132-4ae0-8014-45f87586a32f",
    "source": "Saramin"
  },
  {
    "title": "시니어케어 JAVA 백엔드 개발자 모집",
    "link": "https://www.saramin.co.kr/zf_user/jobs/relay/view?view_type=search&rec_idx=52327733&location=ts&searchword=%EB%B0%B1%EC%97%94%EB%93%9C+%EC%9E%90%EB%B0%94&searchType=search&paid_fl=n&search_uuid=944ec723-8132-4ae0-8014-45f87586a32f",
    "source": "Saramin"
  },
  {
    "title": "[React/React Native · Java/Spring] 프론트엔드·백엔드 개발",
    "link": "https://www.saramin.co.kr/zf_user/jobs/relay/view?view_type=search&rec_idx=51994604&location=ts&searchword=%EB%B0%B1%EC%97%94%EB%93%9C+%EC%9E%90%EB%B0%94&searchType=search&paid_fl=n&search_uuid=944ec723-8132-4ae0-8014-45f87586a32f",
    "source": "Saramin"
  },
  {
    "title": "주식회사 모니본 JAVA백엔드 개발자 모집",
    "link": "https://www.saramin.co.kr/zf_user/jobs/relay/view?view_type=search&rec_idx=52251595&location=ts&searchword=%EB%B0%B1%EC%97%94%EB%93%9C+%EC%9E%90%EB%B0%94&searchType=search&paid_fl=n&search_uuid=944ec723-8132-4ae0-8014-45f87586a32f",
    "source": "Saramin"
  },
  {
    "title": "백엔드 개발자(JAVA / 3~15년 / 팀원)",
    "link": "https://www.saramin.co.kr/zf_user/jobs/relay/view?view_type=search&rec_idx=52253490&location=ts&searchword=%EB%B0%B1%EC%97%94%EB%93%9C+%EC%9E%90%EB%B0%94&searchType=search&paid_fl=n&search_uuid=944ec723-8132-4ae0-8014-45f87586a32f",
    "source": "Saramin"
  },
  {
    "title": "백엔드 개발자 (JAVA/팀장급)",
    "link": "https://www.saramin.co.kr/zf_user/jobs/relay/view?view_type=search&rec_idx=52290807&location=ts&searchword=%EB%B0%B1%EC%97%94%EB%93%9C+%EC%9E%90%EB%B0%94&searchType=search&paid_fl=n&search_uuid=944ec723-8132-4ae0-8014-45f87586a32f",
    "source": "Saramin"
  }
]